{
    "@context": "http://www.shared-canvas.org/ns/context.json",
    "@id": "https://nakamura196.github.io/lire/annotation/anno_list/37ab4369f1e87374c734e43db8258c55_238.json",
    "@type": "sc:AnnotationList",
    "resources": [
        {
            "@context": "http://iiif.io/api/presentation/2/context.json",
            "@id": "https://nakamura196.github.io/lire/annotation/anno_list/37ab4369f1e87374c734e43db8258c55_238.json",
            "@type": "oa:Annotation",
            "motivation": "oa:commenting",
            "on": [
                {
                    "@type": "oa:SpecificResource",
                    "full": "https://iiif.dl.itc.u-tokyo.ac.jp/repo/iiif/7f91ae1e-6ffa-4681-bb0f-862be1bd1cb0/canvas/p238",
                    "selector": {
                        "@type": "oa:Choice",
                        "default": {
                            "@type": "oa:FragmentSelector",
                            "value": "xywh=891,407,3110,4836"
                        },
                        "item": {
                            "@type": "oa:SvgSelector",
                            "value": "<svg xmlns='http://www.w3.org/2000/svg'><path xmlns=\"http://www.w3.org/2000/svg\" d=\"M4001,5243h-3110v-4836h3110v2418.0z\" data-paper-data=\"{&quot;strokeWidth&quot;:1,&quot;rotation&quot;:0,&quot;annotation&quot;:null,&quot;nonHoverStrokeColor&quot;:[&quot;Color&quot;,0,0.74902,1],&quot;editable&quot;:true,&quot;deleteIcon&quot;:null,&quot;rotationIcon&quot;:null,&quot;group&quot;:null}\" id=\"rectangle_62389b77-19f2-4d12-aa7c-0ca7c788b5c3\" fill-opacity=\"0.2\" fill=\"red\" fill-rule=\"nonzero\" stroke=\"red\" stroke-width=\"121.89861\" stroke-linecap=\"butt\" stroke-linejoin=\"miter\" stroke-miterlimit=\"10\" stroke-dasharray=\"\" stroke-dashoffset=\"0\" font-family=\"none\" font-weight=\"none\" font-size=\"none\" text-anchor=\"none\" style=\"mix-blend-mode: normal\"/></svg>"
                        }
                    },
                    "within": {
                        "@id": "https://iiif.dl.itc.u-tokyo.ac.jp/repo/iiif/25201/manifest",
                        "@type": "sc:Manifest"
                    }
                }
            ],
            "resource": [
                {
                    "@type": "dctypes:Text",
                    "chars": "[621]",
                    "format": "text/html"
                }
            ]
        },
        {
            "@context": "http://iiif.io/api/presentation/2/context.json",
            "@id": "https://nakamura196.github.io/lire/annotation/anno_list/37ab4369f1e87374c734e43db8258c55_238.json",
            "@type": "oa:Annotation",
            "motivation": "oa:commenting",
            "on": [
                {
                    "@type": "oa:SpecificResource",
                    "full": "https://iiif.dl.itc.u-tokyo.ac.jp/repo/iiif/7f91ae1e-6ffa-4681-bb0f-862be1bd1cb0/canvas/p238",
                    "selector": {
                        "@type": "oa:Choice",
                        "default": {
                            "@type": "oa:FragmentSelector",
                            "value": "xywh=967,540,2152,1365"
                        },
                        "item": {
                            "@type": "oa:SvgSelector",
                            "value": "<svg xmlns='http://www.w3.org/2000/svg'><path xmlns=\"http://www.w3.org/2000/svg\" d=\"M3119,1905h-2152v-1365h2152v682.5z\" data-paper-data=\"{&quot;strokeWidth&quot;:1,&quot;rotation&quot;:0,&quot;annotation&quot;:null,&quot;nonHoverStrokeColor&quot;:[&quot;Color&quot;,0,0.74902,1],&quot;editable&quot;:true,&quot;deleteIcon&quot;:null,&quot;rotationIcon&quot;:null,&quot;group&quot;:null}\" id=\"rectangle_62389b77-19f2-4d12-aa7c-0ca7c788b5c3\" fill-opacity=\"0.2\" fill=\"red\" fill-rule=\"nonzero\" stroke=\"red\" stroke-width=\"121.89861\" stroke-linecap=\"butt\" stroke-linejoin=\"miter\" stroke-miterlimit=\"10\" stroke-dasharray=\"\" stroke-dashoffset=\"0\" font-family=\"none\" font-weight=\"none\" font-size=\"none\" text-anchor=\"none\" style=\"mix-blend-mode: normal\"/></svg>"
                        }
                    },
                    "within": {
                        "@id": "https://iiif.dl.itc.u-tokyo.ac.jp/repo/iiif/25201/manifest",
                        "@type": "sc:Manifest"
                    }
                }
            ],
            "resource": [
                {
                    "@type": "dctypes:Text",
                    "chars": "[622]",
                    "format": "text/html"
                }
            ]
        },
        {
            "@context": "http://iiif.io/api/presentation/2/context.json",
            "@id": "https://nakamura196.github.io/lire/annotation/anno_list/37ab4369f1e87374c734e43db8258c55_238.json",
            "@type": "oa:Annotation",
            "motivation": "oa:commenting",
            "on": [
                {
                    "@type": "oa:SpecificResource",
                    "full": "https://iiif.dl.itc.u-tokyo.ac.jp/repo/iiif/7f91ae1e-6ffa-4681-bb0f-862be1bd1cb0/canvas/p238",
                    "selector": {
                        "@type": "oa:Choice",
                        "default": {
                            "@type": "oa:FragmentSelector",
                            "value": "xywh=4011,3243,2721,1811"
                        },
                        "item": {
                            "@type": "oa:SvgSelector",
                            "value": "<svg xmlns='http://www.w3.org/2000/svg'><path xmlns=\"http://www.w3.org/2000/svg\" d=\"M6732,5054h-2721v-1811h2721v905.5z\" data-paper-data=\"{&quot;strokeWidth&quot;:1,&quot;rotation&quot;:0,&quot;annotation&quot;:null,&quot;nonHoverStrokeColor&quot;:[&quot;Color&quot;,0,0.74902,1],&quot;editable&quot;:true,&quot;deleteIcon&quot;:null,&quot;rotationIcon&quot;:null,&quot;group&quot;:null}\" id=\"rectangle_62389b77-19f2-4d12-aa7c-0ca7c788b5c3\" fill-opacity=\"0.2\" fill=\"red\" fill-rule=\"nonzero\" stroke=\"red\" stroke-width=\"121.89861\" stroke-linecap=\"butt\" stroke-linejoin=\"miter\" stroke-miterlimit=\"10\" stroke-dasharray=\"\" stroke-dashoffset=\"0\" font-family=\"none\" font-weight=\"none\" font-size=\"none\" text-anchor=\"none\" style=\"mix-blend-mode: normal\"/></svg>"
                        }
                    },
                    "within": {
                        "@id": "https://iiif.dl.itc.u-tokyo.ac.jp/repo/iiif/25201/manifest",
                        "@type": "sc:Manifest"
                    }
                }
            ],
            "resource": [
                {
                    "@type": "dctypes:Text",
                    "chars": "[623]",
                    "format": "text/html"
                }
            ]
        },
        {
            "@context": "http://iiif.io/api/presentation/2/context.json",
            "@id": "https://nakamura196.github.io/lire/annotation/anno_list/37ab4369f1e87374c734e43db8258c55_238.json",
            "@type": "oa:Annotation",
            "motivation": "oa:commenting",
            "on": [
                {
                    "@type": "oa:SpecificResource",
                    "full": "https://iiif.dl.itc.u-tokyo.ac.jp/repo/iiif/7f91ae1e-6ffa-4681-bb0f-862be1bd1cb0/canvas/p238",
                    "selector": {
                        "@type": "oa:Choice",
                        "default": {
                            "@type": "oa:FragmentSelector",
                            "value": "xywh=3916,455,2930,2797"
                        },
                        "item": {
                            "@type": "oa:SvgSelector",
                            "value": "<svg xmlns='http://www.w3.org/2000/svg'><path xmlns=\"http://www.w3.org/2000/svg\" d=\"M6846,3252h-2930v-2797h2930v1398.5z\" data-paper-data=\"{&quot;strokeWidth&quot;:1,&quot;rotation&quot;:0,&quot;annotation&quot;:null,&quot;nonHoverStrokeColor&quot;:[&quot;Color&quot;,0,0.74902,1],&quot;editable&quot;:true,&quot;deleteIcon&quot;:null,&quot;rotationIcon&quot;:null,&quot;group&quot;:null}\" id=\"rectangle_62389b77-19f2-4d12-aa7c-0ca7c788b5c3\" fill-opacity=\"0.2\" fill=\"red\" fill-rule=\"nonzero\" stroke=\"red\" stroke-width=\"121.89861\" stroke-linecap=\"butt\" stroke-linejoin=\"miter\" stroke-miterlimit=\"10\" stroke-dasharray=\"\" stroke-dashoffset=\"0\" font-family=\"none\" font-weight=\"none\" font-size=\"none\" text-anchor=\"none\" style=\"mix-blend-mode: normal\"/></svg>"
                        }
                    },
                    "within": {
                        "@id": "https://iiif.dl.itc.u-tokyo.ac.jp/repo/iiif/25201/manifest",
                        "@type": "sc:Manifest"
                    }
                }
            ],
            "resource": [
                {
                    "@type": "dctypes:Text",
                    "chars": "[624]",
                    "format": "text/html"
                }
            ]
        }
    ]
}