{
    "@context": "http://www.shared-canvas.org/ns/context.json",
    "@id": "https://nakamura196.github.io/lire/annotation/anno_list/48b9c3e428fa8db74de2a9ef823aa6f4_87.json",
    "@type": "sc:AnnotationList",
    "resources": [
        {
            "@context": "http://iiif.io/api/presentation/2/context.json",
            "@id": "https://nakamura196.github.io/lire/annotation/anno_list/48b9c3e428fa8db74de2a9ef823aa6f4_87.json",
            "@type": "oa:Annotation",
            "motivation": "oa:commenting",
            "on": [
                {
                    "@type": "oa:SpecificResource",
                    "full": "https://iiif.dl.itc.u-tokyo.ac.jp/repo/iiif/8e7b55c0-dfce-4166-aca9-57a58f873c67/canvas/p87",
                    "selector": {
                        "@type": "oa:Choice",
                        "default": {
                            "@type": "oa:FragmentSelector",
                            "value": "xywh=717,465,6605,4908"
                        },
                        "item": {
                            "@type": "oa:SvgSelector",
                            "value": "<svg xmlns='http://www.w3.org/2000/svg'><path xmlns=\"http://www.w3.org/2000/svg\" d=\"M7322,5373h-6605v-4908h6605v2454.0z\" data-paper-data=\"{&quot;strokeWidth&quot;:1,&quot;rotation&quot;:0,&quot;annotation&quot;:null,&quot;nonHoverStrokeColor&quot;:[&quot;Color&quot;,0,0.74902,1],&quot;editable&quot;:true,&quot;deleteIcon&quot;:null,&quot;rotationIcon&quot;:null,&quot;group&quot;:null}\" id=\"rectangle_62389b77-19f2-4d12-aa7c-0ca7c788b5c3\" fill-opacity=\"0.2\" fill=\"red\" fill-rule=\"nonzero\" stroke=\"red\" stroke-width=\"121.89861\" stroke-linecap=\"butt\" stroke-linejoin=\"miter\" stroke-miterlimit=\"10\" stroke-dasharray=\"\" stroke-dashoffset=\"0\" font-family=\"none\" font-weight=\"none\" font-size=\"none\" text-anchor=\"none\" style=\"mix-blend-mode: normal\"/></svg>"
                        }
                    },
                    "within": {
                        "@id": "https://iiif.dl.itc.u-tokyo.ac.jp/repo/iiif/25264/manifest",
                        "@type": "sc:Manifest"
                    }
                }
            ],
            "resource": [
                {
                    "@type": "dctypes:Text",
                    "chars": "[399]",
                    "format": "text/html"
                }
            ]
        },
        {
            "@context": "http://iiif.io/api/presentation/2/context.json",
            "@id": "https://nakamura196.github.io/lire/annotation/anno_list/48b9c3e428fa8db74de2a9ef823aa6f4_87.json",
            "@type": "oa:Annotation",
            "motivation": "oa:commenting",
            "on": [
                {
                    "@type": "oa:SpecificResource",
                    "full": "https://iiif.dl.itc.u-tokyo.ac.jp/repo/iiif/8e7b55c0-dfce-4166-aca9-57a58f873c67/canvas/p87",
                    "selector": {
                        "@type": "oa:Choice",
                        "default": {
                            "@type": "oa:FragmentSelector",
                            "value": "xywh=1202,630,1571,2570"
                        },
                        "item": {
                            "@type": "oa:SvgSelector",
                            "value": "<svg xmlns='http://www.w3.org/2000/svg'><path xmlns=\"http://www.w3.org/2000/svg\" d=\"M2773,3200h-1571v-2570h1571v1285.0z\" data-paper-data=\"{&quot;strokeWidth&quot;:1,&quot;rotation&quot;:0,&quot;annotation&quot;:null,&quot;nonHoverStrokeColor&quot;:[&quot;Color&quot;,0,0.74902,1],&quot;editable&quot;:true,&quot;deleteIcon&quot;:null,&quot;rotationIcon&quot;:null,&quot;group&quot;:null}\" id=\"rectangle_62389b77-19f2-4d12-aa7c-0ca7c788b5c3\" fill-opacity=\"0.2\" fill=\"red\" fill-rule=\"nonzero\" stroke=\"red\" stroke-width=\"121.89861\" stroke-linecap=\"butt\" stroke-linejoin=\"miter\" stroke-miterlimit=\"10\" stroke-dasharray=\"\" stroke-dashoffset=\"0\" font-family=\"none\" font-weight=\"none\" font-size=\"none\" text-anchor=\"none\" style=\"mix-blend-mode: normal\"/></svg>"
                        }
                    },
                    "within": {
                        "@id": "https://iiif.dl.itc.u-tokyo.ac.jp/repo/iiif/25264/manifest",
                        "@type": "sc:Manifest"
                    }
                }
            ],
            "resource": [
                {
                    "@type": "dctypes:Text",
                    "chars": "[400]",
                    "format": "text/html"
                }
            ]
        },
        {
            "@context": "http://iiif.io/api/presentation/2/context.json",
            "@id": "https://nakamura196.github.io/lire/annotation/anno_list/48b9c3e428fa8db74de2a9ef823aa6f4_87.json",
            "@type": "oa:Annotation",
            "motivation": "oa:commenting",
            "on": [
                {
                    "@type": "oa:SpecificResource",
                    "full": "https://iiif.dl.itc.u-tokyo.ac.jp/repo/iiif/8e7b55c0-dfce-4166-aca9-57a58f873c67/canvas/p87",
                    "selector": {
                        "@type": "oa:Choice",
                        "default": {
                            "@type": "oa:FragmentSelector",
                            "value": "xywh=4103,484,2948,4772"
                        },
                        "item": {
                            "@type": "oa:SvgSelector",
                            "value": "<svg xmlns='http://www.w3.org/2000/svg'><path xmlns=\"http://www.w3.org/2000/svg\" d=\"M7051,5256h-2948v-4772h2948v2386.0z\" data-paper-data=\"{&quot;strokeWidth&quot;:1,&quot;rotation&quot;:0,&quot;annotation&quot;:null,&quot;nonHoverStrokeColor&quot;:[&quot;Color&quot;,0,0.74902,1],&quot;editable&quot;:true,&quot;deleteIcon&quot;:null,&quot;rotationIcon&quot;:null,&quot;group&quot;:null}\" id=\"rectangle_62389b77-19f2-4d12-aa7c-0ca7c788b5c3\" fill-opacity=\"0.2\" fill=\"red\" fill-rule=\"nonzero\" stroke=\"red\" stroke-width=\"121.89861\" stroke-linecap=\"butt\" stroke-linejoin=\"miter\" stroke-miterlimit=\"10\" stroke-dasharray=\"\" stroke-dashoffset=\"0\" font-family=\"none\" font-weight=\"none\" font-size=\"none\" text-anchor=\"none\" style=\"mix-blend-mode: normal\"/></svg>"
                        }
                    },
                    "within": {
                        "@id": "https://iiif.dl.itc.u-tokyo.ac.jp/repo/iiif/25264/manifest",
                        "@type": "sc:Manifest"
                    }
                }
            ],
            "resource": [
                {
                    "@type": "dctypes:Text",
                    "chars": "[401]",
                    "format": "text/html"
                }
            ]
        },
        {
            "@context": "http://iiif.io/api/presentation/2/context.json",
            "@id": "https://nakamura196.github.io/lire/annotation/anno_list/48b9c3e428fa8db74de2a9ef823aa6f4_87.json",
            "@type": "oa:Annotation",
            "motivation": "oa:commenting",
            "on": [
                {
                    "@type": "oa:SpecificResource",
                    "full": "https://iiif.dl.itc.u-tokyo.ac.jp/repo/iiif/8e7b55c0-dfce-4166-aca9-57a58f873c67/canvas/p87",
                    "selector": {
                        "@type": "oa:Choice",
                        "default": {
                            "@type": "oa:FragmentSelector",
                            "value": "xywh=2851,572,1202,2075"
                        },
                        "item": {
                            "@type": "oa:SvgSelector",
                            "value": "<svg xmlns='http://www.w3.org/2000/svg'><path xmlns=\"http://www.w3.org/2000/svg\" d=\"M4053,2647h-1202v-2075h1202v1037.5z\" data-paper-data=\"{&quot;strokeWidth&quot;:1,&quot;rotation&quot;:0,&quot;annotation&quot;:null,&quot;nonHoverStrokeColor&quot;:[&quot;Color&quot;,0,0.74902,1],&quot;editable&quot;:true,&quot;deleteIcon&quot;:null,&quot;rotationIcon&quot;:null,&quot;group&quot;:null}\" id=\"rectangle_62389b77-19f2-4d12-aa7c-0ca7c788b5c3\" fill-opacity=\"0.2\" fill=\"red\" fill-rule=\"nonzero\" stroke=\"red\" stroke-width=\"121.89861\" stroke-linecap=\"butt\" stroke-linejoin=\"miter\" stroke-miterlimit=\"10\" stroke-dasharray=\"\" stroke-dashoffset=\"0\" font-family=\"none\" font-weight=\"none\" font-size=\"none\" text-anchor=\"none\" style=\"mix-blend-mode: normal\"/></svg>"
                        }
                    },
                    "within": {
                        "@id": "https://iiif.dl.itc.u-tokyo.ac.jp/repo/iiif/25264/manifest",
                        "@type": "sc:Manifest"
                    }
                }
            ],
            "resource": [
                {
                    "@type": "dctypes:Text",
                    "chars": "[402]",
                    "format": "text/html"
                }
            ]
        }
    ]
}