{
    "@context": "http://www.shared-canvas.org/ns/context.json",
    "@id": "https://nakamura196.github.io/lire/annotation/anno_list/48b9c3e428fa8db74de2a9ef823aa6f4_110.json",
    "@type": "sc:AnnotationList",
    "resources": [
        {
            "@context": "http://iiif.io/api/presentation/2/context.json",
            "@id": "https://nakamura196.github.io/lire/annotation/anno_list/48b9c3e428fa8db74de2a9ef823aa6f4_110.json",
            "@type": "oa:Annotation",
            "motivation": "oa:commenting",
            "on": [
                {
                    "@type": "oa:SpecificResource",
                    "full": "https://iiif.dl.itc.u-tokyo.ac.jp/repo/iiif/8e7b55c0-dfce-4166-aca9-57a58f873c67/canvas/p110",
                    "selector": {
                        "@type": "oa:Choice",
                        "default": {
                            "@type": "oa:FragmentSelector",
                            "value": "xywh=2473,2163,1493,2871"
                        },
                        "item": {
                            "@type": "oa:SvgSelector",
                            "value": "<svg xmlns='http://www.w3.org/2000/svg'><path xmlns=\"http://www.w3.org/2000/svg\" d=\"M3966,5034h-1493v-2871h1493v1435.5z\" data-paper-data=\"{&quot;strokeWidth&quot;:1,&quot;rotation&quot;:0,&quot;annotation&quot;:null,&quot;nonHoverStrokeColor&quot;:[&quot;Color&quot;,0,0.74902,1],&quot;editable&quot;:true,&quot;deleteIcon&quot;:null,&quot;rotationIcon&quot;:null,&quot;group&quot;:null}\" id=\"rectangle_62389b77-19f2-4d12-aa7c-0ca7c788b5c3\" fill-opacity=\"0.2\" fill=\"red\" fill-rule=\"nonzero\" stroke=\"red\" stroke-width=\"121.89861\" stroke-linecap=\"butt\" stroke-linejoin=\"miter\" stroke-miterlimit=\"10\" stroke-dasharray=\"\" stroke-dashoffset=\"0\" font-family=\"none\" font-weight=\"none\" font-size=\"none\" text-anchor=\"none\" style=\"mix-blend-mode: normal\"/></svg>"
                        }
                    },
                    "within": {
                        "@id": "https://iiif.dl.itc.u-tokyo.ac.jp/repo/iiif/25264/manifest",
                        "@type": "sc:Manifest"
                    }
                }
            ],
            "resource": [
                {
                    "@type": "dctypes:Text",
                    "chars": "[570]",
                    "format": "text/html"
                }
            ]
        },
        {
            "@context": "http://iiif.io/api/presentation/2/context.json",
            "@id": "https://nakamura196.github.io/lire/annotation/anno_list/48b9c3e428fa8db74de2a9ef823aa6f4_110.json",
            "@type": "oa:Annotation",
            "motivation": "oa:commenting",
            "on": [
                {
                    "@type": "oa:SpecificResource",
                    "full": "https://iiif.dl.itc.u-tokyo.ac.jp/repo/iiif/8e7b55c0-dfce-4166-aca9-57a58f873c67/canvas/p110",
                    "selector": {
                        "@type": "oa:Choice",
                        "default": {
                            "@type": "oa:FragmentSelector",
                            "value": "xywh=1154,1949,1319,3239"
                        },
                        "item": {
                            "@type": "oa:SvgSelector",
                            "value": "<svg xmlns='http://www.w3.org/2000/svg'><path xmlns=\"http://www.w3.org/2000/svg\" d=\"M2473,5188h-1319v-3239h1319v1619.5z\" data-paper-data=\"{&quot;strokeWidth&quot;:1,&quot;rotation&quot;:0,&quot;annotation&quot;:null,&quot;nonHoverStrokeColor&quot;:[&quot;Color&quot;,0,0.74902,1],&quot;editable&quot;:true,&quot;deleteIcon&quot;:null,&quot;rotationIcon&quot;:null,&quot;group&quot;:null}\" id=\"rectangle_62389b77-19f2-4d12-aa7c-0ca7c788b5c3\" fill-opacity=\"0.2\" fill=\"red\" fill-rule=\"nonzero\" stroke=\"red\" stroke-width=\"121.89861\" stroke-linecap=\"butt\" stroke-linejoin=\"miter\" stroke-miterlimit=\"10\" stroke-dasharray=\"\" stroke-dashoffset=\"0\" font-family=\"none\" font-weight=\"none\" font-size=\"none\" text-anchor=\"none\" style=\"mix-blend-mode: normal\"/></svg>"
                        }
                    },
                    "within": {
                        "@id": "https://iiif.dl.itc.u-tokyo.ac.jp/repo/iiif/25264/manifest",
                        "@type": "sc:Manifest"
                    }
                }
            ],
            "resource": [
                {
                    "@type": "dctypes:Text",
                    "chars": "[571]",
                    "format": "text/html"
                }
            ]
        },
        {
            "@context": "http://iiif.io/api/presentation/2/context.json",
            "@id": "https://nakamura196.github.io/lire/annotation/anno_list/48b9c3e428fa8db74de2a9ef823aa6f4_110.json",
            "@type": "oa:Annotation",
            "motivation": "oa:commenting",
            "on": [
                {
                    "@type": "oa:SpecificResource",
                    "full": "https://iiif.dl.itc.u-tokyo.ac.jp/repo/iiif/8e7b55c0-dfce-4166-aca9-57a58f873c67/canvas/p110",
                    "selector": {
                        "@type": "oa:Choice",
                        "default": {
                            "@type": "oa:FragmentSelector",
                            "value": "xywh=4238,1833,1425,1736"
                        },
                        "item": {
                            "@type": "oa:SvgSelector",
                            "value": "<svg xmlns='http://www.w3.org/2000/svg'><path xmlns=\"http://www.w3.org/2000/svg\" d=\"M5663,3569h-1425v-1736h1425v868.0z\" data-paper-data=\"{&quot;strokeWidth&quot;:1,&quot;rotation&quot;:0,&quot;annotation&quot;:null,&quot;nonHoverStrokeColor&quot;:[&quot;Color&quot;,0,0.74902,1],&quot;editable&quot;:true,&quot;deleteIcon&quot;:null,&quot;rotationIcon&quot;:null,&quot;group&quot;:null}\" id=\"rectangle_62389b77-19f2-4d12-aa7c-0ca7c788b5c3\" fill-opacity=\"0.2\" fill=\"red\" fill-rule=\"nonzero\" stroke=\"red\" stroke-width=\"121.89861\" stroke-linecap=\"butt\" stroke-linejoin=\"miter\" stroke-miterlimit=\"10\" stroke-dasharray=\"\" stroke-dashoffset=\"0\" font-family=\"none\" font-weight=\"none\" font-size=\"none\" text-anchor=\"none\" style=\"mix-blend-mode: normal\"/></svg>"
                        }
                    },
                    "within": {
                        "@id": "https://iiif.dl.itc.u-tokyo.ac.jp/repo/iiif/25264/manifest",
                        "@type": "sc:Manifest"
                    }
                }
            ],
            "resource": [
                {
                    "@type": "dctypes:Text",
                    "chars": "[572]",
                    "format": "text/html"
                }
            ]
        },
        {
            "@context": "http://iiif.io/api/presentation/2/context.json",
            "@id": "https://nakamura196.github.io/lire/annotation/anno_list/48b9c3e428fa8db74de2a9ef823aa6f4_110.json",
            "@type": "oa:Annotation",
            "motivation": "oa:commenting",
            "on": [
                {
                    "@type": "oa:SpecificResource",
                    "full": "https://iiif.dl.itc.u-tokyo.ac.jp/repo/iiif/8e7b55c0-dfce-4166-aca9-57a58f873c67/canvas/p110",
                    "selector": {
                        "@type": "oa:Choice",
                        "default": {
                            "@type": "oa:FragmentSelector",
                            "value": "xywh=4355,659,1309,1183"
                        },
                        "item": {
                            "@type": "oa:SvgSelector",
                            "value": "<svg xmlns='http://www.w3.org/2000/svg'><path xmlns=\"http://www.w3.org/2000/svg\" d=\"M5664,1842h-1309v-1183h1309v591.5z\" data-paper-data=\"{&quot;strokeWidth&quot;:1,&quot;rotation&quot;:0,&quot;annotation&quot;:null,&quot;nonHoverStrokeColor&quot;:[&quot;Color&quot;,0,0.74902,1],&quot;editable&quot;:true,&quot;deleteIcon&quot;:null,&quot;rotationIcon&quot;:null,&quot;group&quot;:null}\" id=\"rectangle_62389b77-19f2-4d12-aa7c-0ca7c788b5c3\" fill-opacity=\"0.2\" fill=\"red\" fill-rule=\"nonzero\" stroke=\"red\" stroke-width=\"121.89861\" stroke-linecap=\"butt\" stroke-linejoin=\"miter\" stroke-miterlimit=\"10\" stroke-dasharray=\"\" stroke-dashoffset=\"0\" font-family=\"none\" font-weight=\"none\" font-size=\"none\" text-anchor=\"none\" style=\"mix-blend-mode: normal\"/></svg>"
                        }
                    },
                    "within": {
                        "@id": "https://iiif.dl.itc.u-tokyo.ac.jp/repo/iiif/25264/manifest",
                        "@type": "sc:Manifest"
                    }
                }
            ],
            "resource": [
                {
                    "@type": "dctypes:Text",
                    "chars": "[573]",
                    "format": "text/html"
                }
            ]
        },
        {
            "@context": "http://iiif.io/api/presentation/2/context.json",
            "@id": "https://nakamura196.github.io/lire/annotation/anno_list/48b9c3e428fa8db74de2a9ef823aa6f4_110.json",
            "@type": "oa:Annotation",
            "motivation": "oa:commenting",
            "on": [
                {
                    "@type": "oa:SpecificResource",
                    "full": "https://iiif.dl.itc.u-tokyo.ac.jp/repo/iiif/8e7b55c0-dfce-4166-aca9-57a58f873c67/canvas/p110",
                    "selector": {
                        "@type": "oa:Choice",
                        "default": {
                            "@type": "oa:FragmentSelector",
                            "value": "xywh=1008,669,3094,1358"
                        },
                        "item": {
                            "@type": "oa:SvgSelector",
                            "value": "<svg xmlns='http://www.w3.org/2000/svg'><path xmlns=\"http://www.w3.org/2000/svg\" d=\"M4102,2027h-3094v-1358h3094v679.0z\" data-paper-data=\"{&quot;strokeWidth&quot;:1,&quot;rotation&quot;:0,&quot;annotation&quot;:null,&quot;nonHoverStrokeColor&quot;:[&quot;Color&quot;,0,0.74902,1],&quot;editable&quot;:true,&quot;deleteIcon&quot;:null,&quot;rotationIcon&quot;:null,&quot;group&quot;:null}\" id=\"rectangle_62389b77-19f2-4d12-aa7c-0ca7c788b5c3\" fill-opacity=\"0.2\" fill=\"red\" fill-rule=\"nonzero\" stroke=\"red\" stroke-width=\"121.89861\" stroke-linecap=\"butt\" stroke-linejoin=\"miter\" stroke-miterlimit=\"10\" stroke-dasharray=\"\" stroke-dashoffset=\"0\" font-family=\"none\" font-weight=\"none\" font-size=\"none\" text-anchor=\"none\" style=\"mix-blend-mode: normal\"/></svg>"
                        }
                    },
                    "within": {
                        "@id": "https://iiif.dl.itc.u-tokyo.ac.jp/repo/iiif/25264/manifest",
                        "@type": "sc:Manifest"
                    }
                }
            ],
            "resource": [
                {
                    "@type": "dctypes:Text",
                    "chars": "[574]",
                    "format": "text/html"
                }
            ]
        }
    ]
}